promptev/__init__.py
promptev/client.py
promptev-0.0.3.dist-info/licenses/LICENSE
promptev-0.0.3.dist-info/METADATA
promptev-0.0.3.dist-info/WHEEL
promptev-0.0.3.dist-info/top_level.txt
promptev-0.0.3.dist-info/RECORD
