Metadata-Version: 2.4
Name: promptev
Version: 0.0.3
Summary: Promptev SDK for accessing Promptev API
Author-email: Promptev Inc <support@promptev.ai>
License: Promptev SDK License
Project-URL: Homepage, https://promptev.ai
Keywords: Promptev,promptev,prompts,api,client,sdk,ai,promptDev,promptdev,promptops,python
Requires-Python: >=3.7
License-File: LICENSE
Requires-Dist: httpx
Provides-Extra: cache
Requires-Dist: cachetools>=5.3.0; extra == "cache"
Dynamic: license-file
